{
  "data": [
    {
      "image": "blob:http://localhost:4200/6c0caaef-a87c-483c-9ce9-319f153db4e7",
      "comment": [
        {
          "text": "sda",
          "likes": 0
        }
      ],
      "id": 1
    },
    {
      "image": "blob:http://localhost:4200/6c0caaef-a87c-483c-9ce9-319f153db4e7",
      "comment": [
        {
          "text": "sda",
          "likes": 0
        },
        {
          "text": "sad",
          "likes": 0
        }
      ],
      "id": 2
    },
    {
      "image": "",
      "comment": [
        {
          "text": "ads",
          "likes": 0
        }
      ],
      "id": 3
    },
    {
      "image": "",
      "comment": [
        {
          "text": "ads",
          "likes": 0
        },
        {
          "text": "dsaf",
          "likes": 0
        }
      ],
      "id": 4
    },
    {
      "image": "",
      "comment": [
        {
          "text": "ads",
          "likes": 0
        },
        {
          "text": "dsaf",
          "likes": 0
        },
        {
          "text": "sadff",
          "likes": 0
        }
      ],
      "id": 5
    },
    {
      "image": "blob:http://localhost:4200/11514520-ca9c-4934-84fb-0837349810e8",
      "comment": [
        {
          "text": "fd",
          "likes": 0
        }
      ],
      "id": 6
    },
    {
      "image": "blob:http://localhost:4200/a2af4cd7-6b5d-4f88-952a-18829eef7f4f",
      "comment": [
        {
          "text": "sdds",
          "likes": 0
        }
      ],
      "id": 7
    },
    {
      "image": "blob:http://localhost:4200/9cfb33a8-8459-40c3-a3cd-9327b25feef3",
      "comment": [
        {
          "text": "dsa",
          "likes": 0
        }
      ],
      "id": 8
    },
    {
      "image": "blob:http://localhost:4200/bcba2e0c-a3c9-4c47-b4f4-afee29e27259",
      "comment": [
        {
          "text": "dsaf",
          "likes": 0
        }
      ],
      "id": 9
    },
    {
      "image": "blob:http://localhost:4200/caab4472-b737-4841-9239-362f1b9f4652",
      "comment": [
        {
          "text": "sdfsa",
          "likes": 0
        }
      ],
      "id": 10
    }
  ]
}